Metadata-Version: 1.1
Name: wayround-org-toxcorebot
Version: 0.1
Summary: Tox chat bot based on wayround_org_toxcorebind
Home-page: https://github.com/AnimusPEXUS/wayround_org_toxcorebot
Author: Alexey Gorshkov
Author-email: animus@wayround.org
License: UNKNOWN
Platform: UNKNOWN
Classifier: License :: OSI Approved :: GNU General Public License v3 or later (GPLv3+)
Classifier: Operating System :: POSIX
